{"segments": [{"Time_Start": 0.0, "Time_End": 20.48, "Text": " That there was child porn on IRC."}, {"Time_Start": 20.48, "Time_End": 21.6, "Text": " Please."}, {"Time_Start": 25.6, "Time_End": 29.98, "Text": " Again, when I was informed that there was child pornography on the internet on the internet,"}, {"Time_Start": 30.0, "Time_End": 35.64, "Text": " I was extremely offended and we started an organization that was extremely militant."}, {"Time_Start": 35.64, "Time_End": 42.0, "Text": " We started out as the ACPM, the anti-child porn militia."}, {"Time_Start": 42.0, "Time_End": 48.56, "Text": " Within the first three weeks of our organization, we got 300 volunteers."}, {"Time_Start": 48.56, "Time_End": 51.900000000000006, "Text": " A hundred of those volunteers signed up as hackers."}, {"Time_Start": 51.900000000000006, "Time_End": 58.84, "Text": " We thought that there was a solution, if there's child porn a server, let the boys go out there,"}, {"Time_Start": 58.84, "Time_End": 65.84, "Text": " the server, remove the information. If there was child porn on an ISP, notify them, have them"}, {"Time_Start": 65.84, "Time_End": 71.84, "Text": " to remove that information. As you all know, that information is backed up on CD's other hard drives."}, {"Time_Start": 71.84, "Time_End": 77.84, "Text": " That does absolutely no good. When we came here last year to DEFCOM, we were looking for hackers."}, {"Time_Start": 77.84, "Time_End": 82.84, "Text": " While we were here, one of our board people, one of the people in our organization,"}, {"Time_Start": 82.84, "Time_End": 88.84, "Text": " said something that I've really paid attention to. You cannot stop a felony with a felony."}, {"Time_Start": 88.84, "Time_End": 93.84, "Text": " Our main goal is to put these people in prison."}, {"Time_Start": 93.84, "Time_End": 100.84, "Text": " That is the only way they're going to stop dispensing child pornography and wounding children and killing children."}, {"Time_Start": 100.84, "Time_End": 105.84, "Text": " In order to do that, we had to embrace law enforcement."}, {"Time_Start": 105.84, "Time_End": 117.84, "Text": " We now work directly with law enforcement, other organizations such as missing children, FBI, U.S. Customs, UNESCO."}, {"Time_Start": 117.84, "Time_End": 125.84, "Text": " UNESCO. One of the things that we've done with our hacking community is we've redirected their energy."}, {"Time_Start": 125.84, "Time_End": 131.84, "Text": " And they now are building tools to help us fight child pornography."}, {"Time_Start": 131.84, "Time_End": 137.84, "Text": " We have one tool in particular that goes out and spiders out child porn on the internet."}, {"Time_Start": 137.84, "Time_End": 143.84, "Text": " We are refining that tool according to law enforcement's requirements to do a better job."}, {"Time_Start": 143.84, "Time_End": 147.82, "Text": " If we send in all the reports we get of child pornography, they cannot"}, {"Time_Start": 147.84, "Time_End": 153.84, "Text": " deal with it. It's overwhelming. But if we refine those reports and do part of their job,"}, {"Time_Start": 153.84, "Time_End": 157.84, "Text": " to make their job easier, we have better equipment, we have more time, we have more bandwidth,"}, {"Time_Start": 157.84, "Time_End": 160.84, "Text": " then they can do their job better."}, {"Time_Start": 162.84, "Time_End": 168.84, "Text": " We are now a non-for-profit organization. We have a structure. We have a board of directors."}, {"Time_Start": 168.84, "Time_End": 171.84, "Text": " If you go to our website, look at their bios."}, {"Time_Start": 171.84, "Time_End": 176.84, "Text": " We have businessmen. We have actually two parts to ACPO. We have ACPO. We have ACPO."}, {"Time_Start": 176.84, "Time_End": 177.84, "Text": " We have ACPO."}, {"Time_Start": 177.84, "Time_End": 182.84, "Text": " and we have Team ACPO. Team ACPO is made up of our programmers and our developers."}, {"Time_Start": 182.84, "Time_End": 187.84, "Text": " ACPO, board of directors, myself, go through background checks."}, {"Time_Start": 187.84, "Time_End": 193.84, "Text": " Anybody dealing directly that close with our organization goes to background checks."}, {"Time_Start": 193.84, "Time_End": 195.84, "Text": " Our coders do not."}, {"Time_Start": 195.84, "Time_End": 200.84, "Text": " A few of them do because they're working on specific tools, so we have to check who we're dealing with."}, {"Time_Start": 200.84, "Time_End": 206.84, "Text": " Well, at this point, I think what I'm going to do, we also have a huge liaison program."}, {"Time_Start": 206.84, "Time_End": 210.84, "Text": " program all over the United States, all over the world."}, {"Time_Start": 210.84, "Time_End": 215.84, "Text": " One of the goals of the liaisons is to look for law enforcement contacts."}, {"Time_Start": 215.84, "Time_End": 218.84, "Text": " This is DeQuest."}, {"Time_Start": 218.84, "Time_End": 223.84, "Text": " He's our French liaison and our European representative."}, {"Time_Start": 223.84, "Time_End": 227.84, "Text": " Hi."}, {"Time_Start": 227.84, "Time_End": 231.84, "Text": " Hi, everyone. As she told you, I'm coming from France."}, {"Time_Start": 231.84, "Time_End": 235.84, "Text": " I'll take care of the European part of the European part."}, {"Time_Start": 235.84, "Time_End": 244.84, "Text": " European part of ACPO because this child porn thing is not only a disaster in America,"}, {"Time_Start": 244.84, "Time_End": 253.84, "Text": " but also over Europe, where we do have like a lot of child porn, not only website, but a really"}, {"Time_Start": 253.84, "Time_End": 256.84000000000003, "Text": " well-organized system."}, {"Time_Start": 256.84000000000003, "Time_End": 264.84000000000003, "Text": " One of my job with ACPO is to take care not only to get contacts, like for example, we get"}, {"Time_Start": 264.84000000000003, "Time_End": 273.84000000000003, "Text": " we get really good contacts at the UNESCO, because we are an official, as Natchez-sa previously,"}, {"Time_Start": 273.84000000000003, "Time_End": 279.84000000000003, "Text": " with a non-profit status now. It's like a real organization, not only a website,"}, {"Time_Start": 279.84000000000003, "Time_End": 287.84000000000003, "Text": " and we're trying to build a big network of contacts in official agency all over Europe,"}, {"Time_Start": 287.84000000000003, "Time_End": 293.84000000000003, "Text": " because it's really important to take care of this part of the, of the, of the country."}, {"Time_Start": 293.84000000000003, "Time_End": 295.84000000000003, "Text": " of the continent."}, {"Time_Start": 295.84000000000003, "Time_End": 301.84000000000003, "Text": " The other thing is about the team ACPA was in Natchase previously."}, {"Time_Start": 301.84000000000003, "Time_End": 307.84000000000003, "Text": " We do have many programmers who join us directly by our website"}, {"Time_Start": 307.84000000000003, "Time_End": 312.84000000000003, "Text": " because we're trying to build a lot of tools"}, {"Time_Start": 312.84000000000003, "Time_End": 316.84000000000003, "Text": " in different language, running different platforms,"}, {"Time_Start": 316.84000000000003, "Time_End": 319.84000000000003, "Text": " we can use to automatize the maximum of the tasks"}, {"Time_Start": 319.84000000000003, "Time_End": 322.84000000000003, "Text": " because we went like when we started two years ago,"}, {"Time_Start": 322.84000000000003, "Time_End": 330.08000000000004, "Text": " ago, from single copy and paste, from a submission from the website, to now fitting directly"}, {"Time_Start": 330.08000000000004, "Time_End": 336.84000000000003, "Text": " databases with all the information, all those reports we get from website, from emails, and"}, {"Time_Start": 336.84000000000003, "Time_End": 344.84000000000003, "Text": " it saved a lot of time. It will help us to be more efficient on the result and all the information"}, {"Time_Start": 344.84000000000003, "Time_End": 349.84000000000003, "Text": " we will grab from those reports."}, {"Time_Start": 349.84000000000003, "Time_End": 351.84000000000003, "Text": " The other part, for the information we will grab from those reports."}, {"Time_Start": 351.84000000000003, "Time_End": 352.84000000000003, "Text": " The other part, for the data."}, {"Time_Start": 352.84000000000003, "Time_End": 359.64000000000004, "Text": " Our team ACPO is to build some kind of donationware, is to make some software running"}, {"Time_Start": 359.64000000000004, "Time_End": 366.04, "Text": " on different operating system that family will be able to use at home just to make sure the"}, {"Time_Start": 366.04, "Time_End": 375.04, "Text": " kids are surfing and don't see this kind of pictures or those kind of website."}, {"Time_Start": 375.04, "Time_End": 382.82000000000005, "Text": " So that's one of the biggest plan we got at this time is to release 100% cross-platform software."}, {"Time_Start": 382.84000000000003, "Time_End": 394.84000000000003, "Text": " to filter not only with keywords, but with all the technical parts to prevent this from happening to kids."}, {"Time_Start": 394.84000000000003, "Time_End": 402.84000000000003, "Text": " So we're working on this and that's why we need some programmers for this team ACPO."}, {"Time_Start": 402.84000000000003, "Time_End": 411.84000000000003, "Text": " No matter of the skills you have, it depends, because we will not focus on any language at this time to build this kind of software."}, {"Time_Start": 411.84000000000003, "Time_End": 422.84000000000003, "Text": " or any people with C++ with any language would be really helpful to us."}, {"Time_Start": 422.84000000000003, "Time_End": 428.84000000000003, "Text": " For the website part, for making the software, for creating those databases,"}, {"Time_Start": 428.84000000000003, "Time_End": 434.84000000000003, "Text": " and I think there's a lot of job to do on this part."}, {"Time_Start": 434.84000000000003, "Time_End": 441.82000000000005, "Text": " The other point is about our needs. Of course, we need some not only software, not hard"}, {"Time_Start": 441.84000000000003, "Time_End": 443.84000000000003, "Text": " but we need bandwidth."}, {"Time_Start": 443.84000000000003, "Time_End": 448.84000000000003, "Text": " At this time, all our information are gathered on computers around the world."}, {"Time_Start": 448.84000000000003, "Time_End": 455.84000000000003, "Text": " One of the main aim is to get local and small and pretty secure network operations center"}, {"Time_Start": 455.84000000000003, "Time_End": 462.84000000000003, "Text": " with dedicated line database system, like regular network operations center, sorry."}, {"Time_Start": 462.84000000000003, "Time_End": 470.84000000000003, "Text": " So as a non-profit organization, at this time we're able to receive donations from companies,"}, {"Time_Start": 470.84000000000003, "Time_End": 478.24, "Text": " companies from any people and it already helps us a lot this, I don't know what's"}, {"Time_Start": 478.24, "Time_End": 485.34000000000003, "Text": " a word, it's in America, it's the 501 , that's the technical word for the nonprofit."}, {"Time_Start": 485.34000000000003, "Time_End": 495.48, "Text": " There's a lot of, a lot of things to do with ACPO if you have programming skills,"}, {"Time_Start": 495.48, "Time_End": 500.82000000000005, "Text": " if you have skilled at all. We don't ask for anyone to work like 20,000 people."}, {"Time_Start": 500.84000000000003, "Time_End": 506.84000000000003, "Text": " 24 hours a day, if they just want to spare some time with us, if they feel like doing it,"}, {"Time_Start": 506.84000000000003, "Time_End": 509.84000000000003, "Text": " everyone is welcome, really."}, {"Time_Start": 509.84000000000003, "Time_End": 511.84000000000003, "Text": " Thank you, Diki."}, {"Time_Start": 511.84000000000003, "Time_End": 520.84, "Text": " And we also, as one of our board of directors likes to put it, we're kind of an umbrella that has met with other organizations"}, {"Time_Start": 520.84, "Time_End": 525.84, "Text": " doing basically the same thing we're doing trying to stop child porn on the internet."}, {"Time_Start": 525.84, "Time_End": 530.82, "Text": " We have a sister organization in Germany, anti-kinder porno,"}, {"Time_Start": 530.84, "Time_End": 536.9200000000001, "Text": " who met with us at Myrtle Beach and law enforcement. They've been around for about six years."}, {"Time_Start": 536.9200000000001, "Time_End": 541.8000000000001, "Text": " We have a group in Denmark that we're closely associated with. And at this time, I'd like to introduce"}, {"Time_Start": 541.8000000000001, "Time_End": 547.84, "Text": " you to a locksley from... You never get it right. I don't, I get locks from condemn.org."}, {"Time_Start": 547.84, "Time_End": 556.84, "Text": " I'm R. Locksley. This is Blueberry. This is our Australian component. Some of you may know me"}, {"Time_Start": 556.84, "Time_End": 560.82, "Text": " as kind of the hacker contingent. And we started exactly like"}, {"Time_Start": 560.84, "Time_End": 565.34, "Text": " they did. We didn't call ourselves a militia, although if I had thought of it, we probably"}, {"Time_Start": 565.34, "Time_End": 574.1800000000001, "Text": " would have. We figured that, and it was really Blue and Vort, the other people from Australia,"}, {"Time_Start": 574.6800000000001, "Time_End": 578.5600000000001, "Text": " that started this, they brought up a website, and they knew that I was out there doing it"}, {"Time_Start": 578.5600000000001, "Time_End": 582.7, "Text": " anyway. And they said, hey, you, you're old, you got a big mouth, you want to come and help."}, {"Time_Start": 584.5, "Time_End": 590.76, "Text": " So we kind of got in bed together right away. And we started in the same way. We started going"}, {"Time_Start": 590.84, "Time_End": 597.84, "Text": " and right on the website it says we take child pornographers off the net in any way we can."}, {"Time_Start": 597.84, "Time_End": 598.84, "Text": " What's the exact wording?"}, {"Time_Start": 598.84, "Time_End": 599.84, "Text": " That's about it."}, {"Time_Start": 599.84, "Time_End": 607.84, "Text": " Any way we can. Well, I got hooked up. Some of you know the name most hated, unfortunately now in jail."}, {"Time_Start": 607.84, "Time_End": 613.84, "Text": " But one of the good things that he did was introduce me to Natasha and her crew."}, {"Time_Start": 613.84, "Time_End": 620.82, "Text": " And she said to us, well, you guys are going through what we went through about, you know, what was it a year and a half?"}, {"Time_Start": 620.84, "Time_End": 627.84, "Text": " two years ago. And after many screaming phone calls in the middle of the night and,"}, {"Time_Start": 627.84, "Time_End": 633.84, "Text": " you know, her sitting me down and in the channel and saying, you know, you need to listen,"}, {"Time_Start": 633.84, "Time_End": 638.84, "Text": " I finally came to the realization that as much as I hate to admit it, she's right."}, {"Time_Start": 638.84, "Time_End": 647.84, "Text": " And our group now is 100% legitimate. However, we do have a lot of people that come to us and say,"}, {"Time_Start": 647.84, "Time_End": 650.82, "Text": " listen, we found these sites. What do you want us to do?"}, {"Time_Start": 650.84, "Time_End": 655.84, "Text": " and we tell them we want you to report them on the site and we will take care of them."}, {"Time_Start": 655.84, "Time_End": 660.84, "Text": " Now unfortunately, and I'm hoping my law enforcement contact next to me doesn't shoot me,"}, {"Time_Start": 660.84, "Time_End": 663.84, "Text": " but unfortunately they don't have as much bandwidth as we do."}, {"Time_Start": 663.84, "Time_End": 665.84, "Text": " They don't have as much time."}, {"Time_Start": 665.84, "Time_End": 671.84, "Text": " So what we find is that they'll go and they'll look at the site three or four times, these hackers,"}, {"Time_Start": 671.84, "Time_End": 674.84, "Text": " and if it's not gone, a lot of the time they take it down themselves."}, {"Time_Start": 674.84, "Time_End": 679.84, "Text": " Now, I will not go out and let me step back."}, {"Time_Start": 679.84, "Time_End": 684.84, "Text": " Let me step back. When they come to me, I'll always advise them about the law, as I understand"}, {"Time_Start": 684.84, "Time_End": 689.84, "Text": " it, and I just kind of got my head handed to me. I didn't understand one piece of it."}, {"Time_Start": 689.84, "Time_End": 696.84, "Text": " I've always felt that it was morally right to do this, morally right to go and, you know,"}, {"Time_Start": 696.84, "Time_End": 702.84, "Text": " yeah, it is a felony to perpetrate a felony, but something that I was missing was that when we go out there"}, {"Time_Start": 702.84, "Time_End": 707.84, "Text": " and we hack these sites, a lot of the time we're stealing evidence from people like them"}, {"Time_Start": 707.84, "Time_End": 710.84, "Text": " who were in a legitimate investigation trying to put these people in jail."}, {"Time_Start": 710.84, "Time_End": 715.84, "Text": " And this is what Natasha has been screaming at me about for about the last six months."}, {"Time_Start": 715.84, "Time_End": 722.84, "Text": " So I will not go out and tell a hacker not to hack a pedophile site."}, {"Time_Start": 722.84, "Time_End": 726.84, "Text": " But I will tell them what the legalities are, why you shouldn't do it,"}, {"Time_Start": 726.84, "Time_End": 730.84, "Text": " and explain to them what the consequences are, potential consequences,"}, {"Time_Start": 730.84, "Time_End": 734.84, "Text": " which I just got schooled on this morning, was kind of pretty embarrassing."}, {"Time_Start": 734.84, "Time_End": 736.84, "Text": " But if it's a little bit of,"}, {"Time_Start": 736.84, "Time_End": 744.84, "Text": " But if it's a choice between hacking NASA and a pedophile site, I think everybody knows what recommendation I'm going to give them."}, {"Time_Start": 744.84, "Time_End": 750.84, "Text": " For us, it's been a hard transition because the people that I deal with are hackers."}, {"Time_Start": 750.84, "Time_End": 753.84, "Text": " They are people that want to go out, they want to hack things,"}, {"Time_Start": 753.84, "Time_End": 757.84, "Text": " and they want it to be something that morally right, they can kind of jump on the bandwagon,"}, {"Time_Start": 757.84, "Time_End": 762.84, "Text": " and do something that they can perform an active conscience, which they still do."}, {"Time_Start": 762.84, "Time_End": 765.84, "Text": " Now, I'm trying to change that."}, {"Time_Start": 765.84, "Time_End": 766.84, "Text": " I'm not recruiting."}, {"Time_Start": 766.84, "Time_End": 770.84, "Text": " don't need any bandwidth, don't need web space, don't need anything."}, {"Time_Start": 770.84, "Time_End": 771.84, "Text": " We have all of that."}, {"Time_Start": 771.84, "Time_End": 774.84, "Text": " All I'm saying is that get involved."}, {"Time_Start": 774.84, "Time_End": 778.84, "Text": " You know, whether, you know, we don't, yeah, sure, everybody needs money,"}, {"Time_Start": 778.84, "Time_End": 780.84, "Text": " but we're not looking for that either."}, {"Time_Start": 780.84, "Time_End": 783.84, "Text": " If you know a congressman, senator, anything like that, write them a letter"}, {"Time_Start": 783.84, "Time_End": 786.84, "Text": " and say to them, listen, these guys are right."}, {"Time_Start": 786.84, "Time_End": 792.84, "Text": " They need to, the congressmen and senators need to start changing some of the laws"}, {"Time_Start": 792.84, "Time_End": 794.84, "Text": " to give them teeth."}, {"Time_Start": 794.84, "Time_End": 796.84, "Text": " One of the things that Natasha, I'm really supposed,"}, {"Time_Start": 796.84, "Time_End": 798.84, "Text": " with your mouth that you didn't bring this up."}, {"Time_Start": 798.84, "Time_End": 802.84, "Text": " There is a particular law that we have been looking at"}, {"Time_Start": 802.84, "Time_End": 805.84, "Text": " and we're now actively in the process of trying to change."}, {"Time_Start": 805.84, "Time_End": 809.84, "Text": " If somebody goes out and rapes a child,"}, {"Time_Start": 809.84, "Time_End": 811.84, "Text": " they can get 10 to 20 years."}, {"Time_Start": 811.84, "Time_End": 814.84, "Text": " If that person is related to that child,"}, {"Time_Start": 814.84, "Time_End": 816.84, "Text": " generally they get probation."}, {"Time_Start": 816.84, "Time_End": 818.84, "Text": " We find that unacceptable."}, {"Time_Start": 818.84, "Time_End": 821.84, "Text": " You know, by definition a child trusts that family member,"}, {"Time_Start": 821.84, "Time_End": 825.84, "Text": " and we find it very difficult to set that type of a precedent to a child."}, {"Time_Start": 825.84, "Time_End": 830.84, "Text": " And nobody knows that. That's the thing. So that's one example, please."}, {"Time_Start": 830.84, "Time_End": 834.84, "Text": " Just get on the phone. If you know senators, congressmen, just in your home states."}, {"Time_Start": 834.84, "Time_End": 838.84, "Text": " Just write them a letter and say, go look at condemn.org and see if you can help us."}, {"Time_Start": 838.84, "Time_End": 840.84, "Text": " That's all. That's all I ask."}, {"Time_Start": 840.84, "Time_End": 842.84, "Text": " And did you want to say anything?"}, {"Time_Start": 842.84, "Time_End": 845.84, "Text": " This is Blueberry. Hopefully you can understand her accent."}, {"Time_Start": 845.84, "Time_End": 852.84, "Text": " Hi. I just want, I've had a thought that I really think the industry should start regulating itself."}, {"Time_Start": 852.84, "Time_End": 854.84, "Text": " I'm talking about the people who run web hosting services."}, {"Time_Start": 854.84, "Time_End": 855.84, "Text": " web hosting services."}, {"Time_Start": 855.84, "Time_End": 856.84, "Text": " Yeah."}, {"Time_Start": 856.84, "Time_End": 861.84, "Text": " I think that unless people who start filtering their own content,"}, {"Time_Start": 861.84, "Time_End": 863.84, "Text": " look at what they're putting online before they just put it up."}, {"Time_Start": 863.84, "Time_End": 866.84, "Text": " Otherwise, we're looking at censorship down the line."}, {"Time_Start": 866.84, "Time_End": 870.84, "Text": " You're giving government's reasons to install software that prohibits people viewing things."}, {"Time_Start": 870.84, "Time_End": 871.84, "Text": " We're not for censorship."}, {"Time_Start": 871.84, "Time_End": 874.84, "Text": " With the industry starting to look at what they're putting online,"}, {"Time_Start": 874.84, "Time_End": 877.84, "Text": " if they stop putting it out there, we don't have to take it down anymore."}, {"Time_Start": 877.84, "Time_End": 880.84, "Text": " I mean, sure they're going to move to somewhere else."}, {"Time_Start": 880.84, "Time_End": 883.84, "Text": " Perhaps an easier place for us to catch them online, like IRC, you know?"}, {"Time_Start": 883.84, "Time_End": 890.84, "Text": " like IRC, you know? So if any of you guys are web hosting, check your content first, please, please."}, {"Time_Start": 890.84, "Time_End": 893.84, "Text": " Boy, I didn't think you're going to say anything."}, {"Time_Start": 893.84, "Time_End": 897.84, "Text": " On that note, back to you, Nat. Thank you for listening."}, {"Time_Start": 897.84, "Time_End": 903.84, "Text": " And I'd like to introduce you to Detective Mark Laderman, and he'll tell you more about himself."}, {"Time_Start": 903.84, "Time_End": 907.84, "Text": " My name is Mark Lanerman. I'm a detective from Minneapolis"}, {"Time_Start": 907.84, "Time_End": 911.84, "Text": " and I'm currently assigned to the Minnesota High Tech Crime Task Force."}, {"Time_Start": 913.84, "Time_End": 915.84, "Text": " Yeah, I can't believe no one spotted me."}, {"Time_Start": 915.84, "Time_End": 917.84, "Text": " He's my fad."}, {"Time_Start": 917.84, "Time_End": 923.84, "Text": " Anyway, I can certainly appreciate the frustration"}, {"Time_Start": 923.84, "Time_End": 927.84, "Text": " that several attendees of this convention have"}, {"Time_Start": 927.84, "Time_End": 931.84, "Text": " regarding hacking child porn websites."}, {"Time_Start": 931.84, "Time_End": 936.84, "Text": " However, I do have to caution you that"}, {"Time_Start": 936.84, "Time_End": 939.84, "Text": " if I am investigating a crime,"}, {"Time_Start": 939.84, "Time_End": 943.84, "Text": " if I am investigating an authorized computer access in the state,"}, {"Time_Start": 943.84, "Time_End": 947.84, "Text": " to Minnesota, it is punishable by a five-year felony."}, {"Time_Start": 947.84, "Time_End": 950.84, "Text": " And that's to start with. I don't have to show intent."}, {"Time_Start": 950.84, "Time_End": 953.84, "Text": " I don't have to show damage. I have to show access."}, {"Time_Start": 953.84, "Time_End": 958.84, "Text": " That's very easy for me to do. So I just want to caution you about doing that."}, {"Time_Start": 958.84, "Time_End": 966.84, "Text": " I certainly appreciate the morals behind doing this. I certainly appreciate why someone"}, {"Time_Start": 966.84, "Time_End": 972.84, "Text": " would want to go ahead and do this. And if I wasn't in law enforcement, I don't know what I would be doing about it."}, {"Time_Start": 972.84, "Time_End": 982.84, "Text": " I just don't want to see someone with good intentions get more trouble than what they realized could have happened to them."}, {"Time_Start": 982.84, "Time_End": 984.84, "Text": " Also, I do want to keep this brief."}, {"Time_Start": 984.84, "Time_End": 987.84, "Text": " So I just want to touch on one other topic."}, {"Time_Start": 987.84, "Time_End": 997.84, "Text": " There's this misperception that if someone wants to report child pornography on the web, on the Internet,"}, {"Time_Start": 997.84, "Time_End": 999.84, "Text": " that they want to go to the feds right away."}, {"Time_Start": 999.84, "Time_End": 1002.82, "Text": " Well, believe it or not, your local and state authorities have more"}, {"Time_Start": 1002.84, "Time_End": 1007.84, "Text": " much more authority in dealing with these crimes than the feds do."}, {"Time_Start": 1007.84, "Time_End": 1014.84, "Text": " And I tell you that firsthand, as quite often federal agencies come to me asking for assistance"}, {"Time_Start": 1014.84, "Time_End": 1016.84, "Text": " in Minnesota."}, {"Time_Start": 1016.84, "Time_End": 1021.84, "Text": " So, you know, I don't want to tell you folks, don't go to the feds if you want to report something,"}, {"Time_Start": 1021.84, "Time_End": 1024.8400000000001, "Text": " but certainly try your local and state authorities first also."}, {"Time_Start": 1024.8400000000001, "Time_End": 1025.8400000000001, "Text": " Thank you."}, {"Time_Start": 1025.8400000000001, "Time_End": 1030.8400000000001, "Text": " But if you do find it, report it, please."}, {"Time_Start": 1030.8400000000001, "Time_End": 1032.8400000000001, "Text": " At this point, we are going to open the questions."}, {"Time_Start": 1032.84, "Time_End": 1033.84, "Text": " and answers."}, {"Time_Start": 1033.84, "Time_End": 1034.84, "Text": " Yes, ma'am?"}, {"Time_Start": 1034.84, "Time_End": 1036.84, "Text": " We wanted to keep this real brief because we know it's sandwich."}, {"Time_Start": 1036.84, "Time_End": 1037.84, "Text": " Yes."}, {"Time_Start": 1037.84, "Time_End": 1048.84, "Text": " Well, that's one of the things that we're doing with Team ACP."}, {"Time_Start": 1048.84, "Time_End": 1051.84, "Text": " She wants to know how we're going to know where the website is."}, {"Time_Start": 1051.84, "Time_End": 1054.84, "Text": " That's one of the things that Team ACP has done is written a script now."}, {"Time_Start": 1054.84, "Time_End": 1057.84, "Text": " So all our reports run through a process."}, {"Time_Start": 1057.84, "Time_End": 1062.84, "Text": " And not only do we give them the URL, but we give them the DNS, the IP, who is, all the other"}, {"Time_Start": 1062.84, "Time_End": 1066.84, "Text": " information we can. The next step of that, and that goes off to"}, {"Time_Start": 1066.84, "Time_End": 1070.84, "Text": " nitmick, a missing children, customs, and the feds."}, {"Time_Start": 1070.84, "Time_End": 1074.84, "Text": " After that, if we find that the site is in Alabama,"}, {"Time_Start": 1074.84, "Time_End": 1078.84, "Text": " then if you're the Alabama liaison, you will have given us law enforcement connections"}, {"Time_Start": 1078.84, "Time_End": 1081.84, "Text": " in Alabama. It will be sent to them also."}, {"Time_Start": 1081.84, "Time_End": 1086.84, "Text": " Go, Phil, go."}, {"Time_Start": 1086.84, "Time_End": 1089.84, "Text": " I can actually speak fairly loudly if you want."}, {"Time_Start": 1089.84, "Time_End": 1092.82, "Text": " I'm curious, can you, you can"}, {"Time_Start": 1092.84, "Time_End": 1096.84, "Text": " only do things about sites here in the United States, right? I mean, no."}, {"Time_Start": 1096.84, "Time_End": 1097.84, "Text": " That's..."}, {"Time_Start": 1097.84, "Time_End": 1098.84, "Text": " Really."}, {"Time_Start": 1098.84, "Time_End": 1106.84, "Text": " We have law enforcement contacts in a lot of different places in the world."}, {"Time_Start": 1106.84, "Time_End": 1112.84, "Text": " We are by no means to where we should be in terms of our contacts."}, {"Time_Start": 1112.84, "Time_End": 1116.84, "Text": " So if you know someone, we need help."}, {"Time_Start": 1116.84, "Time_End": 1121.84, "Text": " And we'll never have enough, because it's such a global problem."}, {"Time_Start": 1121.84, "Time_End": 1123.84, "Text": " Nat, you can get me if I talk to me."}, {"Time_Start": 1123.84, "Time_End": 1124.84, "Text": " Go ahead."}, {"Time_Start": 1124.84, "Time_End": 1127.84, "Text": " But it's such a global problem that people just don't understand."}, {"Time_Start": 1127.84, "Time_End": 1129.84, "Text": " It's everywhere."}, {"Time_Start": 1129.84, "Time_End": 1132.84, "Text": " And for every site we take down, you know, 10 are put back up."}, {"Time_Start": 1132.84, "Time_End": 1136.84, "Text": " That's like the time delay is so important with lawn costing as well."}, {"Time_Start": 1136.84, "Time_End": 1141.84, "Text": " If you're looking at eight weeks before they're even viewing the site too long,"}, {"Time_Start": 1141.84, "Time_End": 1142.84, "Text": " it's too long."}, {"Time_Start": 1142.84, "Time_End": 1145.84, "Text": " It has to be changed and it has to come down really fast."}, {"Time_Start": 1145.84, "Time_End": 1146.84, "Text": " It's hard to leave."}, {"Time_Start": 1146.84, "Time_End": 1149.84, "Text": " You've got 20,000 people downloading those images,"}, {"Time_Start": 1149.84, "Time_End": 1150.84, "Text": " putting them straight back up."}, {"Time_Start": 1150.84, "Time_End": 1153.84, "Text": " back up. So you can really please try to love you,"}, {"Time_Start": 1153.84, "Time_End": 1158.84, "Text": " really get law enforcement to cut down these times."}, {"Time_Start": 1158.84, "Time_End": 1161.84, "Text": " This is one of the things that we're doing, too, is we're going to address the..."}, {"Time_Start": 1161.84, "Time_End": 1164.84, "Text": " There are people out there, I didn't know there's porn out there,"}, {"Time_Start": 1164.84, "Time_End": 1166.84, "Text": " but they realize that's child porn."}, {"Time_Start": 1166.84, "Time_End": 1169.84, "Text": " And there's a lot of people that don't behind as child porn."}, {"Time_Start": 1169.84, "Time_End": 1171.84, "Text": " Oh, ladies with computers."}, {"Time_Start": 1171.84, "Time_End": 1173.84, "Text": " Grab the mic."}, {"Time_Start": 1173.84, "Time_End": 1175.84, "Text": " Oh, I think you can't you?"}, {"Time_Start": 1175.84, "Time_End": 1176.84, "Text": " Can't you?"}, {"Time_Start": 1176.84, "Time_End": 1177.84, "Text": " No."}, {"Time_Start": 1177.84, "Time_End": 1178.84, "Text": " Uh, give me."}, {"Time_Start": 1180.84, "Time_End": 1190.84, "Text": " The other thing Blue had said, too, about ISPs,"}, {"Time_Start": 1190.84, "Time_End": 1197.84, "Text": " we do have a letter that is ready to go out to the ISPs, but because of the process and staying legal,"}, {"Time_Start": 1197.84, "Time_End": 1202.84, "Text": " that has to go through all of the board directors that goes to, that has actually gone to the feds,"}, {"Time_Start": 1202.84, "Time_End": 1205.84, "Text": " and that will go out to ISPs now addressing that problem."}, {"Time_Start": 1205.84, "Time_End": 1208.84, "Text": " Something else I wanted to say, too."}, {"Time_Start": 1208.84, "Time_End": 1210.82, "Text": " We were sent some information to"}, {"Time_Start": 1210.84, "Time_End": 1217.84, "Text": " sent over to law enforcement. We were sent 11.5 megs of text off of a child porn"}, {"Time_Start": 1217.84, "Time_End": 1224.84, "Text": " BBS. I spent three hours deleting information that someone, and their good intentions,"}, {"Time_Start": 1224.84, "Time_End": 1229.84, "Text": " had tried to crash that BBS and shut it down. It took me three hours. I had to send it"}, {"Time_Start": 1229.84, "Time_End": 1235.84, "Text": " to a professional organization database. It took them another five hours before we could even"}, {"Time_Start": 1235.84, "Time_End": 1239.84, "Text": " start to look at this information to send the FBI. So a lot of times, like it was mentioned before,"}, {"Time_Start": 1239.84, "Time_End": 1243.84, "Text": " like it was mentioned before. And then the evidence that we had gotten before,"}, {"Time_Start": 1243.84, "Time_End": 1247.84, "Text": " they did eventually shut this BBS down, and a couple others, we lost the evidence that we had"}, {"Time_Start": 1247.84, "Time_End": 1252.84, "Text": " ready for law enforcement. So from my point of view, please, if you know the site,"}, {"Time_Start": 1252.84, "Time_End": 1260.84, "Text": " reported, if you have a problem, you know, mail, don't shut down these, some of them being watched."}, {"Time_Start": 1260.84, "Time_End": 1269.82, "Text": " And that's another point, we agree, because ACPA and condemn that are, I mean, we"}, {"Time_Start": 1269.84, "Time_End": 1279.84, "Text": " we don't have to forget that the main aim is exactly the same, is to prevent to take the child porn from, to take out the child porn from the internet."}, {"Time_Start": 1279.84, "Time_End": 1285.84, "Text": " After, we want to argue you about the way we will do it, it's different organizations."}, {"Time_Start": 1285.84, "Time_End": 1294.84, "Text": " But there is something for sure is we won't cross our, we will cross maybe sometimes our roads on several sides."}, {"Time_Start": 1294.84, "Time_End": 1298.84, "Text": " And that's why exchanging information, it's not because it's two different organizations."}, {"Time_Start": 1298.84, "Time_End": 1304.84, "Text": " because it's two different organizations that we won't speak to each other. That's why today we are at the same table,"}, {"Time_Start": 1304.84, "Time_End": 1311.84, "Text": " is to make sure we don't make them waste some time on the site or if they don't do it,"}, {"Time_Start": 1311.84, "Time_End": 1314.84, "Text": " they don't make us waste some time on the site we're working on."}, {"Time_Start": 1314.84, "Time_End": 1321.84, "Text": " And this is really important to get those kind of contact with all those organizations."}, {"Time_Start": 1321.84, "Time_End": 1327.84, "Text": " Yeah, that's another example."}, {"Time_Start": 1327.84, "Time_End": 1332.84, "Text": " We also, at the time of ACPM, something like a year ago,"}, {"Time_Start": 1332.84, "Time_End": 1338.84, "Text": " one of my friend, Kelm Williams, from H.A."}, {"Time_Start": 1338.84, "Time_End": 1340.84, "Text": " Ethical Akir against Pedophilia."}, {"Time_Start": 1340.84, "Time_End": 1342.84, "Text": " The X Packet Storm, Ken Lewis."}, {"Time_Start": 1342.84, "Time_End": 1344.84, "Text": " Also known as Packet Storm."}, {"Time_Start": 1344.84, "Time_End": 1348.84, "Text": " We were working on the Russian side, like Alpholpics,"}, {"Time_Start": 1348.84, "Time_End": 1353.84, "Text": " because when we're talking about child porn, just forget the 10 years' kids."}, {"Time_Start": 1353.84, "Time_End": 1356.84, "Text": " We're talking about three or four years babies having sex with adults."}, {"Time_Start": 1356.84, "Time_End": 1358.84, "Text": " sex with adults."}, {"Time_Start": 1358.84, "Time_End": 1364.84, "Text": " And we're trying to do the maximum to grab information and to work on this case."}, {"Time_Start": 1364.84, "Time_End": 1368.84, "Text": " And just mail him to know if he had some information and everything."}, {"Time_Start": 1368.84, "Time_End": 1371.84, "Text": " And just told me, mail me back a few minutes after we say,"}, {"Time_Start": 1371.84, "Time_End": 1373.84, "Text": " request, just stop it."}, {"Time_Start": 1373.84, "Time_End": 1376.84, "Text": " We're working on this case for at least six months with Antipal,"}, {"Time_Start": 1376.84, "Time_End": 1381.84, "Text": " which is the equivalent of federal agency in Europe,"}, {"Time_Start": 1381.84, "Time_End": 1384.84, "Text": " but working all over Europe."}, {"Time_Start": 1384.84, "Time_End": 1385.84, "Text": " And I mean, they've been working in Europe."}, {"Time_Start": 1385.84, "Time_End": 1387.4399999999998, "Text": " I mean, they've been working six months."}, {"Time_Start": 1387.4399999999998, "Time_End": 1393.84, "Text": " And if we started to work on this case without trying to get information or anything,"}, {"Time_Start": 1393.84, "Time_End": 1398.84, "Text": " I mean, all their work would have been, what was it word?"}, {"Time_Start": 1398.84, "Time_End": 1399.84, "Text": " For nothing."}, {"Time_Start": 1399.84, "Time_End": 1400.84, "Text": " For nothing."}, {"Time_Start": 1400.84, "Time_End": 1407.84, "Text": " That's why it's really important we're still in contact with all those organizations."}, {"Time_Start": 1407.84, "Time_End": 1412.84, "Text": " Much as I hate to admit it, hacking these sites does destroy evidence, doesn't put the people in jail,"}, {"Time_Start": 1412.84, "Time_End": 1415.84, "Text": " doesn't allow them to be Bubba's girlfriend in jail,"}, {"Time_Start": 1415.84, "Time_End": 1422.4399999999998, "Text": " And so it deprives me of a great pleasure of knowing that they're in there for a long time, really suffering,"}, {"Time_Start": 1422.4399999999998, "Time_End": 1424.6, "Text": " and they can't put their poison back up on the net."}, {"Time_Start": 1424.6, "Time_End": 1430.84, "Text": " So as much as I hate to admit it with my kind of checkered past, they're right."}, {"Time_Start": 1430.84, "Time_End": 1431.84, "Text": " Yes, sir."}, {"Time_Start": 1431.84, "Time_End": 1432.84, "Text": " Unfortunately."}, {"Time_Start": 1432.84, "Time_End": 1438.34, "Text": " In the previous session, the gentleman said that took them three hours to detect who put out the love bug virus."}, {"Time_Start": 1438.34, "Time_End": 1444.84, "Text": " Why does it take you people six months to get one of these sites that everybody's looking at all day long?"}, {"Time_Start": 1444.84, "Time_End": 1445.34, "Text": " Yeah."}, {"Time_Start": 1445.34, "Time_End": 1450.34, "Text": " The thing is what I was saying about this, you're talking about the Russian site I was talking about?"}, {"Time_Start": 1450.34, "Time_End": 1451.34, "Text": " Yeah."}, {"Time_Start": 1451.34, "Time_End": 1461.34, "Text": " This thing is, on the child porn thing, I mean, first when I, when I created, when Natasha created ACPM,"}, {"Time_Start": 1461.34, "Time_End": 1468.34, "Text": " I saw that it was some kind of grandpa having a big couple of kids of porn, child porn on their hard drive."}, {"Time_Start": 1468.34, "Time_End": 1474.34, "Text": " But several cases showed us that it's a real mafia behind this."}, {"Time_Start": 1474.34, "Time_End": 1481.34, "Text": " behind this. It's a well-organized network of child porn. Some people say previously,"}, {"Time_Start": 1481.34, "Time_End": 1487.34, "Text": " if we shut down the site, it's going to be restored. What it means is backed up. They have"}, {"Time_Start": 1487.34, "Time_End": 1493.34, "Text": " several servers. And I mean, it's very well-organized. And what they try to do on this case"}, {"Time_Start": 1493.34, "Time_End": 1498.34, "Text": " is to introduce and send some agents directly in Russia to get into this network."}, {"Time_Start": 1498.34, "Time_End": 1500.34, "Text": " Because this is a real mafia."}, {"Time_Start": 1500.34, "Time_End": 1503.34, "Text": " Yeah, you can't, unfortunately, in some cases, you can't."}, {"Time_Start": 1503.34, "Time_End": 1507.6999999999998, "Text": " In some cases, you can't jeopardize your life to go after these sites."}, {"Time_Start": 1507.78, "Time_End": 1511.1999999999998, "Text": " You have to find a way to get the site down without being killed."}, {"Time_Start": 1512.34, "Time_End": 1513.6999999999998, "Text": " If I may a second?"}, {"Time_Start": 1514.22, "Time_End": 1519.9399999999998, "Text": " Just to go to your question, the Lovebug virus, they also have databases of what people have done."}, {"Time_Start": 1520.54, "Time_End": 1522.04, "Text": " This guy was previously up on the radar."}, {"Time_Start": 1522.6, "Time_End": 1529.56, "Text": " What's going on now is pretty much we're way behind on that level of having information about people and who they are."}, {"Time_Start": 1529.9599999999998, "Time_End": 1531.3799999999999, "Text": " Someday we would love to be there."}, {"Time_Start": 1532.1599999999999, "Time_End": 1533.32, "Text": " And really, that's what's what."}, {"Time_Start": 1533.3400000000001, "Time_End": 1544.2800000000002, "Text": " It's starting to generate now with the work Natasha is doing and Loxi's doing with generating this information, tracking down, and setting up these data warehouses for the lack of a better term."}]}